primeList/__init__.py
primeList/usingRpy.py
primelistGersonMontesinos-0.0.1.dist-info/LICENSE
primelistGersonMontesinos-0.0.1.dist-info/METADATA
primelistGersonMontesinos-0.0.1.dist-info/WHEEL
primelistGersonMontesinos-0.0.1.dist-info/top_level.txt
primelistGersonMontesinos-0.0.1.dist-info/RECORD
