Metadata-Version: 2.1
Name: primelistGersonMontesinos
Version: 0.0.1
Summary: A tool to calculate prime numbers using Rpy2 and Python separately
Home-page: UNKNOWN
Author: Gerson Montesinos
Author-email: gerson_montes97@hotmail.com
License: GNU GPLv3
Keywords: rpy2 and python prime numbers enlisted
Platform: UNKNOWN
Classifier: Programming Language :: Python :: 3
Classifier: License :: OSI Approved :: GNU General Public License v3 (GPLv3)
Classifier: Operating System :: OS Independent
License-File: LICENSE
